JurendeGongju/README.md
JurendeGongju/__init__.py
JurendeGongju/__main__.py
JurendeGongju/file.epub
JurendeGongju/index.html
JurendeGongju/css/__init__.py
JurendeGongju/css/annotations.css
JurendeGongju/css/main.css
JurendeGongju/css/normalize.css
JurendeGongju/css/popup.css
JurendeGongju/font/__init__.py
JurendeGongju/font/fontello.eot
JurendeGongju/font/fontello.svg
JurendeGongju/font/fontello.ttf
JurendeGongju/font/fontello.woff
JurendeGongju/img/__init__.py
JurendeGongju/img/annotator-glyph-sprite.png
JurendeGongju/img/annotator-icon-sprite.png
JurendeGongju/img/apple-touch-icon.png
JurendeGongju/img/cancelfullscreen.png
JurendeGongju/img/close.png
JurendeGongju/img/fullscreen.png
JurendeGongju/img/loader.gif
JurendeGongju/img/menu-icon.png
JurendeGongju/img/save.png
JurendeGongju/img/saved.png
JurendeGongju/img/settings-s.png
JurendeGongju/img/settings.png
JurendeGongju/img/star.png
JurendeGongju/js/__init__.py
JurendeGongju/js/epub.js
JurendeGongju/js/epub.min.js
JurendeGongju/js/epub.min.map
JurendeGongju/js/hooks.min.js
JurendeGongju/js/hooks.min.map
JurendeGongju/js/reader.js
JurendeGongju/js/reader.js.map
JurendeGongju/js/reader.min.js
JurendeGongju/js/reader.min.map
JurendeGongju/js/hooks/__init__.py
JurendeGongju/js/hooks/extensions/__init__.py
JurendeGongju/js/hooks/extensions/highlight.js
JurendeGongju/js/libs/__init__.py
JurendeGongju/js/libs/jquery.min.js
JurendeGongju/js/libs/localforage.min.js
JurendeGongju/js/libs/screenfull.js
JurendeGongju/js/libs/screenfull.min.js
JurendeGongju/js/libs/zip.min.js
JurendeGongju/js/plugins/__init__.py
JurendeGongju/js/plugins/hypothesis.js
JurendeGongju/js/plugins/search.js
jurende_gongju-2022.10.15.0.dist-info/METADATA
jurende_gongju-2022.10.15.0.dist-info/WHEEL
jurende_gongju-2022.10.15.0.dist-info/entry_points.txt
jurende_gongju-2022.10.15.0.dist-info/top_level.txt
jurende_gongju-2022.10.15.0.dist-info/RECORD
